{"last_updated": "14 Jul 2026 14:56 IST", "selected": ["LAURUSLABS", "GRANULES", "ADANIGREEN", "ADANIENT", "NYKAA", "LODHA", "TORNTPHARM", "PRESTIGE", "BIOCON", "ZYDUSLIFE", "AUROPHARMA", "FEDERALBNK", "INDUSINDBK", "SUNPHARMA", "APOLLOHOSP", "ADANIPORTS", "ETERNAL", "BANDHANBNK", "CIPLA", "DIVISLAB", "CHOLAFIN", "LUPIN", "NESTLEIND", "IDFCFIRSTB", "GRASIM", "BAJFINANCE", "FORTIS", "TITAN", "BAJAJ-AUTO", "SHRIRAMFIN", "PIDILITIND", "INDIGO", "MAXHEALTH", "NATIONALUM", "ASIANPAINT", "ICICIBANK", "ALKEM", "EICHERMOT", "BHARTIARTL", "HINDALCO", "JSWSTEEL", "JSWENERGY", "SBIN", "TECHM", "BAJAJFINSV", "ABB", "MARUTI", "COALINDIA", "HDFCBANK", "DRREDDY", "AXISBANK", "TATACONSUM", "SAIL", "M&M", "MFSL", "CONCOR", "HEROMOTOCO", "SBILIFE", "ULTRACEMCO", "SIEMENS", "NHPC", "BPCL", "DABUR", "TATASTEEL", "GODREJCP", "LT", "TRENT", "CANBK", "RECLTD", "HINDUNILVR", "KOTAKBANK", "BRITANNIA", "RELIANCE", "POWERGRID", "ONGC", "BEL", "EMAMILTD", "NTPC", "JIOFIN", "AMBUJACEM", "BANKBARODA", "HAVELLS", "MUTHOOTFIN", "PFC", "APLAPOLLO", "TATAPOWER", "SYNGENE", "HDFCLIFE", "ITC", "JINDALSTEL", "DMART", "TCS", "WIPRO", "IRCTC", "HCLTECH", "INFOSYS", "IRFC", "VEDL"], "scores": {"LAURUSLABS": 1.3702, "GRANULES": 1.3624, "ADANIGREEN": 1.2346, "ADANIENT": 1.0777, "NYKAA": 0.8456, "LODHA": 0.7604, "TORNTPHARM": 0.7494, "PRESTIGE": 0.6096, "BIOCON": 0.5844, "ZYDUSLIFE": 0.5419, "AUROPHARMA": 0.5345, "FEDERALBNK": 0.5321, "INDUSINDBK": 0.5042, "SUNPHARMA": 0.4961, "APOLLOHOSP": 0.4792, "ADANIPORTS": 0.4595, "ETERNAL": 0.4382, "BANDHANBNK": 0.4303, "CIPLA": 0.3782, "DIVISLAB": 0.3724, "CHOLAFIN": 0.3714, "LUPIN": 0.3627, "NESTLEIND": 0.3615, "IDFCFIRSTB": 0.3552, "GRASIM": 0.3431, "BAJFINANCE": 0.3199, "FORTIS": 0.307, "TITAN": 0.2565, "BAJAJ-AUTO": 0.2546, "SHRIRAMFIN": 0.2474, "PIDILITIND": 0.2334, "INDIGO": 0.2092, "MAXHEALTH": 0.1795, "NATIONALUM": 0.1761, "ASIANPAINT": 0.1759, "ICICIBANK": 0.1435, "ALKEM": 0.1429, "EICHERMOT": 0.1402, "BHARTIARTL": 0.1391, "HINDALCO": 0.1129, "JSWSTEEL": 0.1096, "JSWENERGY": 0.0968, "SBIN": 0.0536, "TECHM": 0.0486, "BAJAJFINSV": 0.0401, "ABB": 0.0388, "MARUTI": 0.0295, "COALINDIA": 0.0177, "HDFCBANK": 0.0166, "DRREDDY": 0.0086, "AXISBANK": -0.0278, "TATACONSUM": -0.0325, "SAIL": -0.0345, "M&M": -0.0562, "MFSL": -0.0764, "CONCOR": -0.0767, "HEROMOTOCO": -0.0809, "SBILIFE": -0.0824, "ULTRACEMCO": -0.0942, "SIEMENS": -0.096, "NHPC": -0.1, "BPCL": -0.1014, "DABUR": -0.118, "TATASTEEL": -0.1297, "GODREJCP": -0.1305, "LT": -0.1395, "TRENT": -0.1469, "CANBK": -0.1509, "RECLTD": -0.156, "HINDUNILVR": -0.1667, "KOTAKBANK": -0.1674, "BRITANNIA": -0.1896, "RELIANCE": -0.1939, "POWERGRID": -0.2036, "ONGC": -0.205, "BEL": -0.2221, "EMAMILTD": -0.2264, "NTPC": -0.2285, "JIOFIN": -0.2331, "AMBUJACEM": -0.2402, "BANKBARODA": -0.2559, "HAVELLS": -0.276, "MUTHOOTFIN": -0.2832, "PFC": -0.2884, "APLAPOLLO": -0.2896, "TATAPOWER": -0.3025, "SYNGENE": -0.3132, "HDFCLIFE": -0.3611, "ITC": -0.3633, "JINDALSTEL": -0.3978, "DMART": -0.4062, "TCS": -0.4331, "WIPRO": -0.4468, "IRCTC": -0.4689, "HCLTECH": -0.4789, "INFOSYS": -0.5001, "IRFC": -0.5694, "VEDL": -1.7564}}