{"last_updated": "24 Apr 2026 07:16 IST", "selected": ["NATIONALUM", "ABB", "SIEMENS", "VEDL", "GRANULES", "SAIL", "HINDALCO", "AUROPHARMA", "LAURUSLABS", "JINDALSTEL", "DMART", "POWERGRID", "ONGC", "TATASTEEL", "ADANIPORTS", "BANDHANBNK", "BEL", "TATAPOWER", "NTPC", "FEDERALBNK", "NESTLEIND", "TITAN", "LT", "FORTIS", "DRREDDY", "NYKAA", "SBIN", "ADANIENT", "JSWSTEEL", "SHRIRAMFIN", "AXISBANK", "APOLLOHOSP", "ZYDUSLIFE", "APLAPOLLO", "LUPIN", "TRENT", "MUTHOOTFIN", "BAJAJ-AUTO", "COALINDIA", "TATACONSUM", "TORNTPHARM", "NHPC", "ULTRACEMCO", "HINDUNILVR", "EICHERMOT", "CANBK", "CONCOR", "MFSL", "ETERNAL", "ALKEM", "ICICIBANK", "PRESTIGE", "GRASIM", "BAJFINANCE", "ASIANPAINT", "MAXHEALTH", "GODREJCP", "TMPV", "SUNPHARMA", "EMAMILTD", "PIDILITIND", "BIOCON", "RELIANCE", "BANKBARODA", "INDIGO", "JIOFIN", "CIPLA", "DABUR", "BHARTIARTL", "SBILIFE", "BAJAJFINSV", "ITC", "IDFCFIRSTB", "TECHM", "MARUTI", "M&M", "WIPRO", "IRCTC", "KOTAKBANK", "HAVELLS", "HDFCBANK", "AMBUJACEM", "LODHA", "TCS", "HDFCLIFE", "INFY", "HCLTECH", "SYNGENE"], "scores": {"NATIONALUM": 1.5988, "ABB": 1.5023, "SIEMENS": 1.0397, "VEDL": 0.8137, "GRANULES": 0.8, "SAIL": 0.7758, "HINDALCO": 0.7674, "AUROPHARMA": 0.7058, "LAURUSLABS": 0.6692, "JINDALSTEL": 0.647, "DMART": 0.6185, "POWERGRID": 0.6109, "ONGC": 0.6085, "TATASTEEL": 0.5993, "ADANIPORTS": 0.5984, "BANDHANBNK": 0.5885, "BEL": 0.5125, "TATAPOWER": 0.5058, "NTPC": 0.4838, "FEDERALBNK": 0.4808, "NESTLEIND": 0.4269, "TITAN": 0.4076, "LT": 0.4056, "FORTIS": 0.4033, "DRREDDY": 0.3809, "NYKAA": 0.3675, "SBIN": 0.3417, "ADANIENT": 0.3243, "JSWSTEEL": 0.3235, "SHRIRAMFIN": 0.3105, "AXISBANK": 0.3082, "APOLLOHOSP": 0.2926, "ZYDUSLIFE": 0.2864, "APLAPOLLO": 0.2713, "LUPIN": 0.2672, "TRENT": 0.264, "MUTHOOTFIN": 0.2639, "BAJAJ-AUTO": 0.1915, "COALINDIA": 0.1903, "TATACONSUM": 0.1675, "TORNTPHARM": 0.1574, "NHPC": 0.14, "ULTRACEMCO": 0.106, "HINDUNILVR": 0.1042, "EICHERMOT": 0.0961, "CANBK": 0.0884, "CONCOR": 0.0633, "MFSL": 0.0594, "ETERNAL": 0.0518, "ALKEM": 0.0485, "ICICIBANK": 0.018, "PRESTIGE": 0.0176, "GRASIM": 0.0101, "BAJFINANCE": 0.0045, "ASIANPAINT": -0.0041, "MAXHEALTH": -0.0053, "GODREJCP": -0.0447, "TMPV": -0.0448, "SUNPHARMA": -0.0516, "EMAMILTD": -0.0657, "PIDILITIND": -0.088, "BIOCON": -0.1152, "RELIANCE": -0.1204, "BANKBARODA": -0.1249, "INDIGO": -0.1327, "JIOFIN": -0.1427, "CIPLA": -0.1492, "DABUR": -0.1505, "BHARTIARTL": -0.1792, "SBILIFE": -0.2015, "BAJAJFINSV": -0.2345, "ITC": -0.2397, "IDFCFIRSTB": -0.2503, "TECHM": -0.2593, "MARUTI": -0.2598, "M&M": -0.2661, "WIPRO": -0.2989, "IRCTC": -0.3278, "KOTAKBANK": -0.3311, "HAVELLS": -0.3819, "HDFCBANK": -0.3875, "AMBUJACEM": -0.4009, "LODHA": -0.4368, "TCS": -0.4554, "HDFCLIFE": -0.4982, "INFY": -0.5864, "HCLTECH": -0.5939, "SYNGENE": -0.8024}}