{"last_updated": "16 Apr 2026 14:34 IST", "selected": ["HINDALCO", "TATASTEEL", "ONGC", "BEL", "POWERGRID", "ADANIPORTS", "SHRIRAMFIN", "TITAN", "NTPC", "LT", "AXISBANK", "BAJAJ-AUTO", "SBIN", "JSWSTEEL", "EICHERMOT", "APOLLOHOSP", "ADANIENT", "TRENT", "ULTRACEMCO", "SBILIFE", "TECHM", "COALINDIA", "ETERNAL", "NESTLEIND", "GRASIM", "DRREDDY", "ICICIBANK", "M&M", "BAJFINANCE", "INDIGO", "TMPV", "MAXHEALTH", "SUNPHARMA", "TATACONSUM", "HCLTECH", "BAJAJFINSV", "BHARTIARTL", "RELIANCE", "ASIANPAINT", "KOTAKBANK", "JIOFIN", "MARUTI", "HINDUNILVR", "ITC", "INFY", "WIPRO", "HDFCLIFE", "HDFCBANK", "TCS", "CIPLA"], "scores": {"HINDALCO": 0.8245, "TATASTEEL": 0.7752, "ONGC": 0.6837, "BEL": 0.5428, "POWERGRID": 0.538, "ADANIPORTS": 0.4724, "SHRIRAMFIN": 0.4274, "TITAN": 0.4205, "NTPC": 0.4184, "LT": 0.4058, "AXISBANK": 0.3721, "BAJAJ-AUTO": 0.3492, "SBIN": 0.3298, "JSWSTEEL": 0.2779, "EICHERMOT": 0.1662, "APOLLOHOSP": 0.1419, "ADANIENT": 0.1356, "TRENT": 0.1126, "ULTRACEMCO": 0.097, "SBILIFE": 0.0865, "TECHM": 0.0824, "COALINDIA": 0.0601, "ETERNAL": 0.0518, "NESTLEIND": 0.0304, "GRASIM": 0.0207, "DRREDDY": 0.0095, "ICICIBANK": -0.0019, "M&M": -0.0068, "BAJFINANCE": -0.0206, "INDIGO": -0.0436, "TMPV": -0.0437, "MAXHEALTH": -0.0829, "SUNPHARMA": -0.0907, "TATACONSUM": -0.1138, "HCLTECH": -0.1192, "BAJAJFINSV": -0.1352, "BHARTIARTL": -0.139, "RELIANCE": -0.1453, "ASIANPAINT": -0.189, "KOTAKBANK": -0.2274, "JIOFIN": -0.2287, "MARUTI": -0.2444, "HINDUNILVR": -0.2559, "ITC": -0.2805, "INFY": -0.3147, "WIPRO": -0.3515, "HDFCLIFE": -0.3555, "HDFCBANK": -0.3727, "TCS": -0.4064, "CIPLA": -0.4503}}