{"last_updated": "01 Jul 2026 15:47 IST", "selected": ["ADANIGREEN", "ADANIENT", "LAURUSLABS", "PRESTIGE", "GRANULES", "FEDERALBNK", "CHOLAFIN", "NYKAA", "ADANIPORTS", "BANDHANBNK", "LODHA", "IDFCFIRSTB", "INDIGO", "SHRIRAMFIN", "TRENT", "BAJFINANCE", "ZYDUSLIFE", "ASIANPAINT", "AUROPHARMA", "TORNTPHARM", "PIDILITIND", "NESTLEIND", "ETERNAL", "APOLLOHOSP", "FORTIS", "MAXHEALTH", "CIPLA", "INDUSINDBK", "GRASIM", "BIOCON", "MARUTI", "AXISBANK", "RECLTD", "LT", "SIEMENS", "BANKBARODA", "JSWENERGY", "ICICIBANK", "ABB", "SBIN", "BAJAJ-AUTO", "TITAN", "SUNPHARMA", "LUPIN", "EICHERMOT", "DRREDDY", "ALKEM", "KOTAKBANK", "MFSL", "BPCL", "DIVISLAB", "PFC", "BAJAJFINSV", "HINDUNILVR", "ULTRACEMCO", "DABUR", "CONCOR", "JSWSTEEL", "NHPC", "SAIL", "HDFCBANK", "CANBK", "GODREJCP", "M&M", "BHARTIARTL", "HINDALCO", "TATACONSUM", "SYNGENE", "DMART", "EMAMILTD", "NTPC", "HEROMOTOCO", "SBILIFE", "BEL", "POWERGRID", "JIOFIN", "ITC", "COALINDIA", "HAVELLS", "TATASTEEL", "BRITANNIA", "RELIANCE", "APLAPOLLO", "HDFCLIFE", "AMBUJACEM", "NATIONALUM", "TATAPOWER", "IRCTC", "IRFC", "MUTHOOTFIN", "TECHM", "JINDALSTEL", "ONGC", "WIPRO", "TCS", "HCLTECH", "INFOSYS", "VEDL"], "scores": {"ADANIGREEN": 1.9175, "ADANIENT": 1.5985, "LAURUSLABS": 1.5034, "PRESTIGE": 0.9832, "GRANULES": 0.9514, "FEDERALBNK": 0.8967, "CHOLAFIN": 0.8966, "NYKAA": 0.8906, "ADANIPORTS": 0.8678, "BANDHANBNK": 0.8472, "LODHA": 0.8299, "IDFCFIRSTB": 0.7682, "INDIGO": 0.7544, "SHRIRAMFIN": 0.7304, "TRENT": 0.7188, "BAJFINANCE": 0.6737, "ZYDUSLIFE": 0.6685, "ASIANPAINT": 0.6373, "AUROPHARMA": 0.5999, "TORNTPHARM": 0.5954, "PIDILITIND": 0.5828, "NESTLEIND": 0.5824, "ETERNAL": 0.5806, "APOLLOHOSP": 0.5332, "FORTIS": 0.5327, "MAXHEALTH": 0.5296, "CIPLA": 0.5248, "INDUSINDBK": 0.5201, "GRASIM": 0.5128, "BIOCON": 0.4772, "MARUTI": 0.4584, "AXISBANK": 0.4347, "RECLTD": 0.3996, "LT": 0.3844, "SIEMENS": 0.3753, "BANKBARODA": 0.3716, "JSWENERGY": 0.3586, "ICICIBANK": 0.3562, "ABB": 0.3488, "SBIN": 0.3353, "BAJAJ-AUTO": 0.3299, "TITAN": 0.3246, "SUNPHARMA": 0.3056, "LUPIN": 0.2917, "EICHERMOT": 0.2873, "DRREDDY": 0.2803, "ALKEM": 0.254, "KOTAKBANK": 0.2422, "MFSL": 0.2195, "BPCL": 0.2154, "DIVISLAB": 0.2086, "PFC": 0.2057, "BAJAJFINSV": 0.1706, "HINDUNILVR": 0.1703, "ULTRACEMCO": 0.1614, "DABUR": 0.1604, "CONCOR": 0.1521, "JSWSTEEL": 0.1502, "NHPC": 0.1484, "SAIL": 0.1412, "HDFCBANK": 0.1321, "CANBK": 0.1307, "GODREJCP": 0.118, "M&M": 0.1105, "BHARTIARTL": 0.0819, "HINDALCO": 0.055, "TATACONSUM": 0.0544, "SYNGENE": 0.0376, "DMART": 0.0247, "EMAMILTD": 0.0164, "NTPC": 0.0089, "HEROMOTOCO": 0.0074, "SBILIFE": 0.0074, "BEL": 0.0038, "POWERGRID": -0.0116, "JIOFIN": -0.0154, "ITC": -0.0518, "COALINDIA": -0.0542, "HAVELLS": -0.0656, "TATASTEEL": -0.0759, "BRITANNIA": -0.0918, "RELIANCE": -0.118, "APLAPOLLO": -0.1213, "HDFCLIFE": -0.129, "AMBUJACEM": -0.1362, "NATIONALUM": -0.1436, "TATAPOWER": -0.158, "IRCTC": -0.2268, "IRFC": -0.2302, "MUTHOOTFIN": -0.2318, "TECHM": -0.2663, "JINDALSTEL": -0.2963, "ONGC": -0.4759, "WIPRO": -0.585, "TCS": -0.6762, "HCLTECH": -0.8065, "INFOSYS": -0.8112, "VEDL": -1.6958}}