[{"date":"2026-04-19","symbol":"NTPC","signal":"STRONG BUY","price_at_signal":393.6,"expected_return":20.61,"prob_up":0.7809,"sharpe":0.558},{"date":"2026-04-19","symbol":"ONGC","signal":"STRONG BUY","price_at_signal":284.05,"expected_return":20.32,"prob_up":0.7526,"sharpe":0.495},{"date":"2026-04-19","symbol":"POWERGRID","signal":"STRONG BUY","price_at_signal":318.1,"expected_return":19.75,"prob_up":0.7072,"sharpe":0.411},{"date":"2026-04-19","symbol":"APOLLOHOSP","signal":"STRONG BUY","price_at_signal":7699.0,"expected_return":14.74,"prob_up":0.7088,"sharpe":0.32},{"date":"2026-04-19","symbol":"ADANIENT","signal":"BUY","price_at_signal":2218.3,"expected_return":23.77,"prob_up":0.6361,"sharpe":0.364},{"date":"2026-04-19","symbol":"TMPV","signal":"BUY","price_at_signal":360.15,"expected_return":22.06,"prob_up":0.6244,"sharpe":0.332},{"date":"2026-04-19","symbol":"TRENT","signal":"BUY","price_at_signal":4107.7,"expected_return":21.71,"prob_up":0.6141,"sharpe":0.314},{"date":"2026-04-19","symbol":"ADANIPORTS","signal":"BUY","price_at_signal":1573.4,"expected_return":19.48,"prob_up":0.625,"sharpe":0.301},{"date":"2026-04-19","symbol":"TATASTEEL","signal":"BUY","price_at_signal":212.12,"expected_return":18.91,"prob_up":0.6798,"sharpe":0.359},{"date":"2026-04-19","symbol":"AXISBANK","signal":"BUY","price_at_signal":1359.1,"expected_return":15.89,"prob_up":0.6601,"sharpe":0.285},{"date":"2026-04-19","symbol":"MAXHEALTH","signal":"BUY","price_at_signal":1007.65,"expected_return":13.84,"prob_up":0.6551,"sharpe":0.239},{"date":"2026-04-19","symbol":"BEL","signal":"BUY","price_at_signal":462.75,"expected_return":13.65,"prob_up":0.6136,"sharpe":0.197},{"date":"2026-04-19","symbol":"JSWSTEEL","signal":"BUY","price_at_signal":1240.3,"expected_return":13.09,"prob_up":0.6179,"sharpe":0.189},{"date":"2026-04-19","symbol":"ITC","signal":"BUY","price_at_signal":306.8,"expected_return":9.3,"prob_up":0.6386,"sharpe":0.098},{"date":"2026-04-19","symbol":"SHRIRAMFIN","signal":"HOLD","price_at_signal":1036.95,"expected_return":13.21,"prob_up":0.5236,"sharpe":0.122},{"date":"2026-04-19","symbol":"INDIGO","signal":"HOLD","price_at_signal":4638.4,"expected_return":12.82,"prob_up":0.5276,"sharpe":0.119},{"date":"2026-04-19","symbol":"SBIN","signal":"HOLD","price_at_signal":1080.25,"expected_return":11.47,"prob_up":0.6197,"sharpe":0.154},{"date":"2026-04-19","symbol":"DRREDDY","signal":"HOLD","price_at_signal":1235.7,"expected_return":9.29,"prob_up":0.6141,"sharpe":0.086},{"date":"2026-04-19","symbol":"RELIANCE","signal":"HOLD","price_at_signal":1365.0,"expected_return":8.66,"prob_up":0.5864,"sharpe":0.055},{"date":"2026-04-19","symbol":"BHARTIARTL","signal":"HOLD","price_at_signal":1846.9,"expected_return":7.21,"prob_up":0.6002,"sharpe":0.001},{"date":"2026-04-19","symbol":"JIOFIN","signal":"HOLD","price_at_signal":243.86,"expected_return":10.96,"prob_up":0.5389,"sharpe":0.092},{"date":"2026-04-19","symbol":"LT","signal":"HOLD","price_at_signal":4096.1,"expected_return":10.85,"prob_up":0.5375,"sharpe":0.09},{"date":"2026-04-19","symbol":"M&M","signal":"HOLD","price_at_signal":3200.2,"expected_return":10.39,"prob_up":0.534,"sharpe":0.079},{"date":"2026-04-19","symbol":"HINDALCO","signal":"HOLD","price_at_signal":1039.0,"expected_return":10.36,"prob_up":0.5639,"sharpe":0.092},{"date":"2026-04-19","symbol":"COALINDIA","signal":"HOLD","price_at_signal":438.75,"expected_return":10.33,"prob_up":0.5768,"sharpe":0.098},{"date":"2026-04-19","symbol":"ULTRACEMCO","signal":"HOLD","price_at_signal":11886.0,"expected_return":10.28,"prob_up":0.5427,"sharpe":0.08},{"date":"2026-04-19","symbol":"BAJFINANCE","signal":"HOLD","price_at_signal":908.25,"expected_return":9.7,"prob_up":0.5569,"sharpe":0.073},{"date":"2026-04-19","symbol":"BAJAJFINSV","signal":"HOLD","price_at_signal":1838.9,"expected_return":9.46,"prob_up":0.5579,"sharpe":0.068},{"date":"2026-04-19","symbol":"ETERNAL","signal":"HOLD","price_at_signal":252.61,"expected_return":9.1,"prob_up":0.507,"sharpe":0.045},{"date":"2026-04-19","symbol":"TITAN","signal":"HOLD","price_at_signal":4525.9,"expected_return":9.01,"prob_up":0.5611,"sharpe":0.057},{"date":"2026-04-19","symbol":"GRASIM","signal":"HOLD","price_at_signal":2720.5,"expected_return":8.67,"prob_up":0.5773,"sharpe":0.052},{"date":"2026-04-19","symbol":"HDFCBANK","signal":"HOLD","price_at_signal":799.9,"expected_return":8.22,"prob_up":0.5334,"sharpe":0.03},{"date":"2026-04-19","symbol":"ICICIBANK","signal":"HOLD","price_at_signal":1346.8,"expected_return":7.85,"prob_up":0.5632,"sharpe":0.023},{"date":"2026-04-19","symbol":"BAJAJ-AUTO","signal":"HOLD","price_at_signal":9773.5,"expected_return":7.82,"prob_up":0.5608,"sharpe":0.022},{"date":"2026-04-19","symbol":"KOTAKBANK","signal":"HOLD","price_at_signal":383.6,"expected_return":7.77,"prob_up":0.5661,"sharpe":0.021},{"date":"2026-04-19","symbol":"MARUTI","signal":"HOLD","price_at_signal":13453.0,"expected_return":7.51,"prob_up":0.5533,"sharpe":0.011},{"date":"2026-04-19","symbol":"WIPRO","signal":"HOLD","price_at_signal":204.32,"expected_return":7.48,"prob_up":0.5478,"sharpe":0.01},{"date":"2026-04-19","symbol":"EICHERMOT","signal":"RISKY","price_at_signal":7189.5,"expected_return":8.54,"prob_up":0.498,"sharpe":0.031},{"date":"2026-04-19","symbol":"INFY","signal":"RISKY","price_at_signal":1318.7,"expected_return":6.99,"prob_up":0.5474,"sharpe":-0.006},{"date":"2026-04-19","symbol":"SBILIFE","signal":"RISKY","price_at_signal":1970.9,"expected_return":6.93,"prob_up":0.5521,"sharpe":-0.008},{"date":"2026-04-19","symbol":"HCLTECH","signal":"RISKY","price_at_signal":1442.3,"expected_return":6.91,"prob_up":0.5605,"sharpe":-0.01},{"date":"2026-04-19","symbol":"TECHM","signal":"RISKY","price_at_signal":1511.4,"expected_return":6.9,"prob_up":0.5458,"sharpe":-0.009},{"date":"2026-04-19","symbol":"SUNPHARMA","signal":"RISKY","price_at_signal":1675.5,"expected_return":6.82,"prob_up":0.574,"sharpe":-0.015},{"date":"2026-04-19","symbol":"HDFCLIFE","signal":"RISKY","price_at_signal":616.45,"expected_return":6.72,"prob_up":0.5332,"sharpe":-0.014},{"date":"2026-04-19","symbol":"ASIANPAINT","signal":"RISKY","price_at_signal":2464.0,"expected_return":6.29,"prob_up":0.5458,"sharpe":-0.032},{"date":"2026-04-19","symbol":"TCS","signal":"RISKY","price_at_signal":2581.5,"expected_return":6.26,"prob_up":0.5536,"sharpe":-0.035},{"date":"2026-04-19","symbol":"TATACONSUM","signal":"RISKY","price_at_signal":1113.2,"expected_return":6.03,"prob_up":0.5658,"sharpe":-0.049},{"date":"2026-04-19","symbol":"CIPLA","signal":"RISKY","price_at_signal":1240.8,"expected_return":5.55,"prob_up":0.573,"sharpe":-0.078},{"date":"2026-04-19","symbol":"NESTLEIND","signal":"RISKY","price_at_signal":1285.6,"expected_return":5.23,"prob_up":0.5599,"sharpe":-0.087},{"date":"2026-04-19","symbol":"HINDUNILVR","signal":"RISKY","price_at_signal":2240.8,"expected_return":4.34,"prob_up":0.5056,"sharpe":-0.092},{"date":"2026-04-20","symbol":"NTPC","signal":"STRONG BUY","price_at_signal":398.0,"expected_return":20.61,"prob_up":0.7766,"sharpe":0.548},{"date":"2026-04-20","symbol":"ONGC","signal":"STRONG BUY","price_at_signal":283.35,"expected_return":20.32,"prob_up":0.7649,"sharpe":0.518},{"date":"2026-04-20","symbol":"POWERGRID","signal":"STRONG BUY","price_at_signal":319.7,"expected_return":19.76,"prob_up":0.7256,"sharpe":0.44},{"date":"2026-04-20","symbol":"APOLLOHOSP","signal":"STRONG BUY","price_at_signal":7657.0,"expected_return":13.77,"prob_up":0.6985,"sharpe":0.282},{"date":"2026-04-20","symbol":"ADANIENT","signal":"BUY","price_at_signal":2229.6,"expected_return":24.45,"prob_up":0.6559,"sharpe":0.396},{"date":"2026-04-20","symbol":"TMPV","signal":"BUY","price_at_signal":355.6,"expected_return":22.07,"prob_up":0.6265,"sharpe":0.334},{"date":"2026-04-20","symbol":"TRENT","signal":"BUY","price_at_signal":4242.8,"expected_return":21.71,"prob_up":0.6117,"sharpe":0.31},{"date":"2026-04-20","symbol":"ADANIPORTS","signal":"BUY","price_at_signal":1578.4,"expected_return":21.35,"prob_up":0.6657,"sharpe":0.374},{"date":"2026-04-20","symbol":"TATASTEEL","signal":"BUY","price_at_signal":211.72,"expected_return":18.38,"prob_up":0.6791,"sharpe":0.35},{"date":"2026-04-20","symbol":"AXISBANK","signal":"BUY","price_at_signal":1354.7,"expected_return":16.37,"prob_up":0.6701,"sharpe":0.306},{"date":"2026-04-20","symbol":"JSWSTEEL","signal":"BUY","price_at_signal":1274.5,"expected_return":16.1,"prob_up":0.6346,"sharpe":0.262},{"date":"2026-04-20","symbol":"MAXHEALTH","signal":"BUY","price_at_signal":1011.35,"expected_return":13.83,"prob_up":0.6592,"sharpe":0.242},{"date":"2026-04-20","symbol":"BEL","signal":"BUY","price_at_signal":457.55,"expected_return":13.66,"prob_up":0.6182,"sharpe":0.201},{"date":"2026-04-20","symbol":"INDIGO","signal":"BUY","price_at_signal":4678.2,"expected_return":16.55,"prob_up":0.5722,"sharpe":0.206},{"date":"2026-04-20","symbol":"DRREDDY","signal":"BUY","price_at_signal":1232.6,"expected_return":11.29,"prob_up":0.6498,"sharpe":0.17},{"date":"2026-04-20","symbol":"ITC","signal":"BUY","price_at_signal":305.0,"expected_return":10.47,"prob_up":0.6679,"sharpe":0.157},{"date":"2026-04-20","symbol":"SHRIRAMFIN","signal":"HOLD","price_at_signal":1045.15,"expected_return":13.22,"prob_up":0.5359,"sharpe":0.13},{"date":"2026-04-20","symbol":"LT","signal":"HOLD","price_at_signal":4051.0,"expected_return":12.23,"prob_up":0.5611,"sharpe":0.129},{"date":"2026-04-20","symbol":"COALINDIA","signal":"HOLD","price_at_signal":441.75,"expected_return":11.34,"prob_up":0.5918,"sharpe":0.131},{"date":"2026-04-20","symbol":"SBIN","signal":"HOLD","price_at_signal":1107.85,"expected_return":11.08,"prob_up":0.5842,"sharpe":0.12},{"date":"2026-04-20","symbol":"GRASIM","signal":"HOLD","price_at_signal":2760.1,"expected_return":10.9,"prob_up":0.6073,"sharpe":0.13},{"date":"2026-04-20","symbol":"RELIANCE","signal":"HOLD","price_at_signal":1363.3,"expected_return":8.66,"prob_up":0.5965,"sharpe":0.058},{"date":"2026-04-20","symbol":"BHARTIARTL","signal":"HOLD","price_at_signal":1846.1,"expected_return":7.21,"prob_up":0.6035,"sharpe":0.0},{"date":"2026-04-20","symbol":"ULTRACEMCO","signal":"HOLD","price_at_signal":11917.0,"expected_return":11.52,"prob_up":0.5625,"sharpe":0.116},{"date":"2026-04-20","symbol":"JIOFIN","signal":"HOLD","price_at_signal":237.15,"expected_return":10.96,"prob_up":0.5374,"sharpe":0.092},{"date":"2026-04-20","symbol":"M&M","signal":"HOLD","price_at_signal":3221.6,"expected_return":10.4,"prob_up":0.5419,"sharpe":0.082},{"date":"2026-04-20","symbol":"BAJFINANCE","signal":"HOLD","price_at_signal":917.75,"expected_return":9.7,"prob_up":0.5557,"sharpe":0.073},{"date":"2026-04-20","symbol":"BAJAJFINSV","signal":"HOLD","price_at_signal":1830.6,"expected_return":9.46,"prob_up":0.5632,"sharpe":0.07},{"date":"2026-04-20","symbol":"ETERNAL","signal":"HOLD","price_at_signal":254.88,"expected_return":9.13,"prob_up":0.5134,"sharpe":0.047},{"date":"2026-04-20","symbol":"TITAN","signal":"HOLD","price_at_signal":4513.0,"expected_return":9.04,"prob_up":0.5644,"sharpe":0.059},{"date":"2026-04-20","symbol":"HINDALCO","signal":"HOLD","price_at_signal":1015.25,"expected_return":8.93,"prob_up":0.5443,"sharpe":0.05},{"date":"2026-04-20","symbol":"EICHERMOT","signal":"HOLD","price_at_signal":7243.0,"expected_return":8.55,"prob_up":0.5049,"sharpe":0.033},{"date":"2026-04-20","symbol":"HDFCBANK","signal":"HOLD","price_at_signal":795.45,"expected_return":8.23,"prob_up":0.5477,"sharpe":0.033},{"date":"2026-04-20","symbol":"ICICIBANK","signal":"HOLD","price_at_signal":1356.2,"expected_return":7.85,"prob_up":0.5678,"sharpe":0.024},{"date":"2026-04-20","symbol":"BAJAJ-AUTO","signal":"HOLD","price_at_signal":9803.0,"expected_return":7.83,"prob_up":0.565,"sharpe":0.023},{"date":"2026-04-20","symbol":"KOTAKBANK","signal":"HOLD","price_at_signal":379.2,"expected_return":7.77,"prob_up":0.5682,"sharpe":0.021},{"date":"2026-04-20","symbol":"MARUTI","signal":"HOLD","price_at_signal":13450.0,"expected_return":7.52,"prob_up":0.5632,"sharpe":0.012},{"date":"2026-04-20","symbol":"WIPRO","signal":"HOLD","price_at_signal":202.48,"expected_return":7.48,"prob_up":0.5501,"sharpe":0.01},{"date":"2026-04-20","symbol":"INFY","signal":"RISKY","price_at_signal":1312.6,"expected_return":6.99,"prob_up":0.5493,"sharpe":-0.006},{"date":"2026-04-20","symbol":"SBILIFE","signal":"RISKY","price_at_signal":1982.5,"expected_return":6.94,"prob_up":0.5559,"sharpe":-0.009},{"date":"2026-04-20","symbol":"HCLTECH","signal":"RISKY","price_at_signal":1428.3,"expected_return":6.91,"prob_up":0.5608,"sharpe":-0.01},{"date":"2026-04-20","symbol":"TECHM","signal":"RISKY","price_at_signal":1504.4,"expected_return":6.9,"prob_up":0.5465,"sharpe":-0.009},{"date":"2026-04-20","symbol":"HDFCLIFE","signal":"RISKY","price_at_signal":609.75,"expected_return":6.72,"prob_up":0.5357,"sharpe":-0.014},{"date":"2026-04-20","symbol":"ASIANPAINT","signal":"RISKY","price_at_signal":2516.8,"expected_return":6.28,"prob_up":0.5342,"sharpe":-0.029},{"date":"2026-04-20","symbol":"SUNPHARMA","signal":"RISKY","price_at_signal":1668.6,"expected_return":6.27,"prob_up":0.5682,"sharpe":-0.038},{"date":"2026-04-20","symbol":"TCS","signal":"RISKY","price_at_signal":2579.6,"expected_return":6.26,"prob_up":0.556,"sharpe":-0.035},{"date":"2026-04-20","symbol":"TATACONSUM","signal":"RISKY","price_at_signal":1120.4,"expected_return":6.04,"prob_up":0.5669,"sharpe":-0.049},{"date":"2026-04-20","symbol":"CIPLA","signal":"RISKY","price_at_signal":1229.5,"expected_return":5.55,"prob_up":0.5743,"sharpe":-0.078},{"date":"2026-04-20","symbol":"NESTLEIND","signal":"RISKY","price_at_signal":1286.4,"expected_return":5.23,"prob_up":0.5678,"sharpe":-0.093},{"date":"2026-04-20","symbol":"HINDUNILVR","signal":"RISKY","price_at_signal":2231.5,"expected_return":4.36,"prob_up":0.5418,"sharpe":-0.123}]